{
  "@id": "/de",
  "@type": "LRF",
  "UID": "1f58fedb9e2f49d688e920c912b85013",
  "allow_discussion": null,
  "contributors": [],
  "created": "2024-03-08T08:53:33+00:00",
  "creators": [
    "admin"
  ],
  "description": "",
  "effective": null,
  "exclude_from_nav": true,
  "expires": null,
  "exportimport.constrains": {},
  "exportimport.conversation": [],
  "id": "de",
  "is_folderish": true,
  "language": "de",
  "layout": "folder_listing",
  "lock": {},
  "modified": "2025-02-09T07:05:13+00:00",
  "review_state": "published",
  "rights": null,
  "subjects": [],
  "title": "Deutsch",
  "type_title": "Language Root Folder",
  "version": "current",
  "workflow_history": {
    "simple_publication_workflow": [
      {
        "action": null,
        "actor": "admin",
        "comments": "",
        "review_state": "private",
        "time": "2024-03-08T08:53:33+00:00"
      },
      {
        "action": "publish",
        "actor": "admin",
        "comments": "",
        "review_state": "published",
        "time": "2024-03-08T08:53:33+00:00"
      }
    ]
  },
  "working_copy": null,
  "working_copy_of": null
}
